{"meta": {"location": "Royalty Sports Performance", "generated_ms": 1783893771182, "window_days": 30, "business_hours": {"tz": "America/Chicago", "open": "08:00", "close": "18:00", "workdays": [0, 1, 2, 3, 4, 5, 6]}, "lead_count": 725}, "buckets": ["<5m", "5\u201315m", "15\u201330m", "30\u201360m", "1\u20132h", "2\u20134h", "4h+"], "days": ["Sun", "Mon", "Tue", "Wed", "Thu", "Fri", "Sat"], "windows": [{"key": "7d", "label": "7 days", "days": 7}, {"key": "14d", "label": "14 days", "days": 14}, {"key": "30d", "label": "30 days", "days": 30}], "data": {"7d": {"heatmap": [[2, 3, 0, 0, 0, 2, 3, 7, 1, 2, 0, 0, 0, 1, 1, 1, 2, 1, 0, 1, 0, 0, 1, 0], [0, 1, 1, 2, 0, 0, 1, 2, 1, 3, 1, 0, 1, 4, 4, 3, 1, 0, 0, 2, 0, 1, 3, 1], [0, 1, 0, 0, 0, 1, 1, 1, 1, 1, 1, 1, 0, 1, 2, 3, 3, 2, 1, 2, 2, 3, 0, 1], [1, 0, 0, 0, 0, 1, 1, 0, 1, 1, 0, 1, 0, 1, 2, 3, 1, 2, 1, 1, 1, 1, 0, 0], [1, 0, 0, 0, 0, 0, 0, 2, 2, 0, 0, 2, 2, 3, 0, 0, 0, 0, 1, 0, 0, 2, 1, 1], [1, 0, 0, 0, 0, 1, 3, 2, 3, 3, 0, 0, 1, 0, 1, 1, 1, 0, 0, 2, 2, 0, 0, 1], [1, 2, 0, 0, 0, 0, 1, 0, 2, 2, 0, 0, 2, 0, 0, 0, 1, 2, 0, 1, 1, 2, 0, 0]], "bh": {"total": 163, "responded": 106, "noResp": 57, "rate": 65.0, "avg": 10273.238433962264, "median": 3352.549, "p90": 26398.407, "calls": 90, "texts": 16, "dist": [37, 10, 3, 5, 13, 10, 28], "perRep": [{"rep": "Joe Molenaar", "leads": 69, "share": 42.3, "noResp": 1, "avg": 6708.560588235294, "median": 508.59700000000004, "p90": 11410.147, "dist": [32, 8, 2, 4, 8, 8, 6]}, {"rep": "Mike Wandmaker", "leads": 38, "share": 23.3, "noResp": 0, "avg": 16652.13563157895, "median": 18136.27, "p90": 36000.0, "dist": [5, 2, 1, 1, 5, 2, 22]}, {"rep": "Unassigned", "leads": 56, "share": 34.4, "noResp": 56, "avg": null, "median": null, "p90": null, "dist": [0, 0, 0, 0, 0, 0, 0]}]}, "raw": {"total": 163, "responded": 106, "noResp": 57, "rate": 65.0, "avg": 19381.25303773585, "median": 3352.549, "p90": 55901.891, "calls": 90, "texts": 16, "dist": [33, 11, 3, 8, 8, 12, 31], "perRep": [{"rep": "Joe Molenaar", "leads": 69, "share": 42.3, "noResp": 1, "avg": 13283.941720588235, "median": 674.1095, "p90": 15525.062, "dist": [29, 9, 2, 6, 5, 8, 9]}, {"rep": "Mike Wandmaker", "leads": 38, "share": 23.3, "noResp": 0, "avg": 30292.231184210526, "median": 22865.8935, "p90": 71501.425, "dist": [4, 2, 1, 2, 3, 4, 22]}, {"rep": "Unassigned", "leads": 56, "share": 34.4, "noResp": 56, "avg": null, "median": null, "p90": null, "dist": [0, 0, 0, 0, 0, 0, 0]}]}, "repActivity": {"Joe Molenaar": {"dials": 98, "answered": 93, "answerRate": 94.9, "over3": 5, "over3Rate": 5.1, "talkSec": 3400, "avgCallSec": 37, "texts": 70, "emails": 3, "totalTouches": 170, "avgTouchesPerLead": 2.5, "touchDist": [15, 17, 30, 6], "leadsOwned": 69, "replied": 18, "replyRate": 26.1, "heatmap": [[0, 0, 0, 0, 0, 0, 0, 0, 0, 2, 10, 15, 0, 0, 1, 0, 0, 1, 0, 0, 0, 0, 0, 0], [0, 0, 0, 0, 0, 0, 0, 0, 2, 0, 2, 0, 0, 12, 9, 7, 0, 0, 0, 0, 0, 0, 0, 0], [0, 0, 0, 0, 0, 0, 0, 0, 0, 0, 3, 0, 0, 5, 9, 0, 3, 3, 0, 1, 3, 2, 0, 0], [0, 0, 0, 0, 0, 0, 0, 0, 0, 2, 3, 3, 5, 0, 7, 10, 3, 0, 0, 2, 0, 0, 0, 0], [0, 0, 0, 0, 0, 0, 0, 0, 0, 4, 0, 0, 3, 9, 0, 1, 0, 0, 4, 1, 0, 0, 0, 0], [0, 0, 0, 0, 0, 0, 0, 1, 0, 3, 11, 0, 0, 0, 1, 0, 3, 0, 0, 0, 2, 0, 0, 0], [0, 0, 0, 0, 0, 0, 0, 0, 0, 1, 0, 0, 0, 0, 0, 0, 0, 0, 0, 0, 0, 2, 0, 0]]}, "Mike Wandmaker": {"dials": 70, "answered": 66, "answerRate": 94.3, "over3": 3, "over3Rate": 4.3, "talkSec": 2133, "avgCallSec": 32, "texts": 27, "emails": 10, "totalTouches": 107, "avgTouchesPerLead": 2.8, "touchDist": [1, 6, 30, 1], "leadsOwned": 38, "replied": 8, "replyRate": 21.1, "heatmap": [[0, 0, 0, 0, 0, 0, 0, 0, 0, 0, 0, 0, 0, 0, 0, 0, 0, 0, 0, 0, 0, 0, 0, 0], [0, 0, 0, 0, 0, 0, 0, 0, 0, 0, 0, 5, 1, 22, 0, 6, 0, 0, 0, 8, 0, 0, 0, 0], [0, 0, 0, 0, 0, 0, 0, 0, 0, 0, 0, 0, 0, 0, 6, 0, 0, 0, 37, 0, 0, 0, 0, 0], [0, 0, 0, 0, 0, 0, 0, 0, 0, 0, 0, 0, 2, 15, 2, 3, 0, 0, 0, 0, 0, 0, 0, 0], [0, 0, 0, 0, 0, 0, 0, 0, 0, 0, 0, 0, 0, 0, 0, 0, 0, 0, 0, 0, 0, 0, 0, 0], [0, 0, 0, 0, 0, 0, 0, 0, 0, 0, 0, 0, 0, 0, 0, 0, 0, 0, 0, 0, 0, 0, 0, 0], [0, 0, 0, 0, 0, 0, 0, 0, 0, 0, 0, 0, 0, 0, 0, 0, 0, 0, 0, 0, 0, 0, 0, 0]]}}}, "14d": {"heatmap": [[5, 5, 0, 1, 0, 2, 4, 7, 1, 3, 3, 0, 0, 2, 1, 3, 5, 3, 2, 2, 2, 1, 3, 5], [0, 1, 1, 2, 0, 2, 1, 3, 3, 4, 4, 2, 5, 4, 8, 4, 3, 0, 3, 3, 1, 3, 4, 2], [0, 2, 0, 0, 1, 1, 4, 2, 2, 3, 4, 3, 0, 1, 4, 4, 7, 3, 2, 3, 2, 4, 1, 1], [1, 0, 0, 1, 0, 2, 1, 2, 3, 4, 2, 3, 0, 1, 3, 3, 1, 2, 2, 2, 2, 1, 2, 0], [2, 1, 0, 0, 1, 0, 0, 4, 4, 1, 1, 3, 4, 4, 0, 0, 1, 2, 1, 2, 3, 5, 4, 2], [3, 0, 0, 0, 0, 1, 4, 4, 4, 3, 1, 1, 4, 4, 1, 4, 3, 0, 1, 2, 3, 0, 1, 1], [1, 2, 1, 0, 0, 0, 3, 1, 3, 3, 6, 0, 2, 1, 0, 1, 2, 6, 1, 1, 2, 2, 0, 0]], "bh": {"total": 343, "responded": 275, "noResp": 68, "rate": 80.2, "avg": 39902.33328363636, "median": 15331.633, "p90": 158516.662, "calls": 241, "texts": 34, "dist": [67, 15, 3, 8, 20, 21, 141], "perRep": [{"rep": "Carson Fossum", "leads": 1, "share": 0.3, "noResp": 0, "avg": 0.0, "median": 0.0, "p90": 0.0, "dist": [1, 0, 0, 0, 0, 0, 0]}, {"rep": "Joe Molenaar", "leads": 139, "share": 40.5, "noResp": 3, "avg": 19553.41417647059, "median": 871.0325, "p90": 61466.534, "dist": [56, 13, 2, 7, 11, 12, 35]}, {"rep": "Mike Wandmaker", "leads": 138, "share": 40.2, "noResp": 0, "avg": 60245.48786231884, "median": 25682.344, "p90": 191301.59999999998, "dist": [10, 2, 1, 1, 9, 9, 106]}, {"rep": "Unassigned", "leads": 65, "share": 19.0, "noResp": 65, "avg": null, "median": null, "p90": null, "dist": [0, 0, 0, 0, 0, 0, 0]}]}, "raw": {"total": 343, "responded": 275, "noResp": 68, "rate": 80.2, "avg": 89539.32768727273, "median": 17266.779, "p90": 368012.41, "calls": 241, "texts": 34, "dist": [56, 18, 6, 11, 13, 25, 146], "perRep": [{"rep": "Carson Fossum", "leads": 1, "share": 0.3, "noResp": 0, "avg": 614.117, "median": 614.117, "p90": 614.117, "dist": [0, 1, 0, 0, 0, 0, 0]}, {"rep": "Joe Molenaar", "leads": 139, "share": 40.5, "noResp": 3, "avg": 43693.45511029412, "median": 1748.882, "p90": 162266.534, "dist": [50, 15, 3, 8, 8, 12, 40]}, {"rep": "Mike Wandmaker", "leads": 138, "share": 40.2, "noResp": 0, "avg": 135365.15291304348, "median": 55622.366, "p90": 443301.6, "dist": [6, 2, 3, 3, 5, 13, 106]}, {"rep": "Unassigned", "leads": 65, "share": 19.0, "noResp": 65, "avg": null, "median": null, "p90": null, "dist": [0, 0, 0, 0, 0, 0, 0]}]}, "repActivity": {"Carson Fossum": {"dials": 0, "answered": 0, "answerRate": 0, "over3": 0, "over3Rate": 0, "talkSec": 0, "avgCallSec": 0, "texts": 5, "emails": 0, "totalTouches": 5, "avgTouchesPerLead": 5.0, "touchDist": [0, 0, 0, 1], "leadsOwned": 1, "replied": 1, "replyRate": 100.0, "heatmap": [[0, 0, 0, 0, 0, 0, 0, 0, 0, 0, 0, 0, 0, 0, 0, 0, 0, 0, 0, 0, 0, 0, 0, 0], [0, 0, 0, 0, 0, 0, 0, 0, 0, 0, 0, 0, 0, 0, 0, 0, 0, 0, 0, 0, 0, 0, 0, 0], [0, 0, 0, 0, 0, 0, 0, 0, 0, 0, 0, 0, 0, 0, 0, 0, 0, 0, 0, 0, 0, 0, 0, 0], [0, 0, 0, 0, 0, 0, 0, 0, 0, 0, 0, 0, 0, 0, 0, 0, 0, 0, 0, 0, 0, 0, 0, 0], [0, 0, 0, 0, 0, 0, 0, 0, 0, 0, 0, 0, 0, 0, 0, 0, 0, 0, 0, 0, 0, 0, 0, 0], [0, 0, 0, 0, 0, 0, 0, 0, 0, 0, 0, 0, 0, 0, 0, 0, 0, 0, 0, 0, 0, 0, 2, 3], [0, 0, 0, 0, 0, 0, 0, 0, 0, 0, 0, 0, 0, 0, 0, 0, 0, 0, 0, 0, 0, 0, 0, 0]]}, "Joe Molenaar": {"dials": 192, "answered": 182, "answerRate": 94.8, "over3": 11, "over3Rate": 5.7, "talkSec": 8927, "avgCallSec": 49, "texts": 151, "emails": 9, "totalTouches": 349, "avgTouchesPerLead": 2.5, "touchDist": [30, 37, 56, 13], "leadsOwned": 139, "replied": 39, "replyRate": 28.1, "heatmap": [[0, 0, 0, 0, 0, 0, 0, 0, 0, 2, 10, 15, 0, 0, 1, 2, 1, 2, 0, 0, 0, 0, 0, 0], [0, 0, 0, 0, 0, 0, 0, 0, 2, 0, 5, 0, 5, 29, 28, 22, 7, 0, 0, 2, 0, 0, 0, 0], [0, 0, 0, 0, 0, 0, 0, 0, 0, 2, 3, 6, 2, 8, 14, 10, 8, 3, 0, 1, 3, 2, 0, 0], [0, 0, 0, 0, 0, 0, 0, 0, 1, 11, 10, 4, 5, 0, 8, 19, 3, 0, 1, 2, 0, 0, 0, 0], [0, 0, 0, 0, 0, 0, 0, 0, 0, 4, 0, 2, 17, 9, 1, 1, 14, 0, 4, 2, 1, 0, 0, 0], [0, 0, 0, 0, 0, 0, 0, 2, 3, 4, 11, 1, 1, 1, 1, 3, 4, 0, 0, 0, 2, 0, 0, 0], [0, 0, 0, 0, 0, 0, 0, 0, 0, 1, 2, 0, 0, 0, 0, 0, 0, 0, 0, 0, 0, 2, 0, 0]]}, "Mike Wandmaker": {"dials": 258, "answered": 236, "answerRate": 91.5, "over3": 7, "over3Rate": 2.7, "talkSec": 6611, "avgCallSec": 28, "texts": 116, "emails": 21, "totalTouches": 394, "avgTouchesPerLead": 2.9, "touchDist": [6, 18, 106, 8], "leadsOwned": 138, "replied": 28, "replyRate": 20.3, "heatmap": [[0, 0, 0, 0, 0, 0, 0, 0, 0, 0, 0, 0, 0, 0, 0, 0, 0, 0, 0, 1, 0, 0, 0, 0], [0, 0, 0, 0, 0, 0, 0, 0, 0, 0, 0, 8, 1, 23, 31, 30, 0, 0, 0, 10, 0, 0, 0, 0], [0, 0, 0, 0, 0, 0, 0, 1, 1, 0, 0, 0, 0, 20, 25, 24, 0, 0, 49, 23, 0, 0, 0, 0], [0, 0, 0, 0, 0, 0, 0, 0, 0, 0, 0, 0, 2, 65, 30, 27, 14, 0, 4, 0, 0, 0, 0, 0], [0, 0, 0, 0, 0, 0, 0, 0, 0, 0, 0, 0, 0, 0, 4, 2, 0, 0, 0, 0, 0, 0, 0, 0], [0, 0, 0, 0, 0, 0, 0, 0, 0, 0, 0, 0, 0, 0, 0, 0, 0, 0, 0, 0, 0, 0, 0, 0], [0, 0, 0, 0, 0, 0, 0, 0, 0, 0, 0, 0, 0, 0, 0, 0, 0, 0, 0, 0, 0, 0, 0, 0]]}}}, "30d": {"heatmap": [[13, 5, 2, 1, 0, 3, 10, 16, 5, 7, 8, 2, 4, 5, 7, 4, 7, 4, 4, 3, 8, 2, 4, 6], [2, 3, 1, 2, 0, 4, 3, 4, 4, 6, 6, 4, 9, 6, 11, 10, 8, 0, 6, 7, 8, 7, 8, 2], [1, 2, 1, 0, 1, 2, 8, 7, 5, 4, 5, 6, 1, 5, 5, 6, 10, 6, 6, 7, 5, 8, 4, 4], [1, 0, 0, 2, 1, 3, 2, 4, 7, 6, 2, 3, 2, 3, 5, 5, 2, 4, 5, 5, 6, 3, 5, 0], [4, 1, 0, 0, 2, 1, 7, 8, 8, 5, 1, 5, 6, 4, 1, 2, 5, 3, 1, 2, 7, 9, 7, 4], [7, 0, 0, 0, 0, 2, 7, 5, 5, 5, 4, 4, 6, 6, 4, 8, 7, 3, 2, 5, 4, 3, 4, 3], [5, 4, 1, 0, 0, 3, 7, 9, 8, 5, 8, 6, 9, 2, 1, 2, 7, 9, 4, 3, 3, 4, 1, 1]], "bh": {"total": 725, "responded": 648, "noResp": 77, "rate": 89.4, "avg": 34700.65796450617, "median": 7977.179, "p90": 128061.17, "calls": 519, "texts": 129, "dist": [180, 32, 11, 25, 71, 60, 269], "perRep": [{"rep": "Joe Molenaar", "leads": 357, "share": 49.2, "noResp": 3, "avg": 12512.574717514124, "median": 1694.213, "p90": 31755.809, "dist": [149, 25, 4, 18, 38, 43, 77]}, {"rep": "Carson Fossum", "leads": 10, "share": 1.4, "noResp": 0, "avg": 16066.268900000001, "median": 12678.0335, "p90": 36000.0, "dist": [4, 1, 0, 0, 0, 0, 5]}, {"rep": "Mike Wandmaker", "leads": 284, "share": 39.2, "noResp": 0, "avg": 63013.775429577465, "median": 25775.0055, "p90": 186862.26099999997, "dist": [27, 6, 7, 7, 33, 17, 187]}, {"rep": "Unassigned", "leads": 74, "share": 10.2, "noResp": 74, "avg": null, "median": null, "p90": null, "dist": [0, 0, 0, 0, 0, 0, 0]}]}, "raw": {"total": 725, "responded": 648, "noResp": 77, "rate": 89.4, "avg": 80198.39325771604, "median": 15115.197, "p90": 288664.219, "calls": 519, "texts": 129, "dist": [150, 37, 15, 27, 35, 56, 328], "perRep": [{"rep": "Carson Fossum", "leads": 10, "share": 1.4, "noResp": 0, "avg": 17537.8662, "median": 13340.752, "p90": 39778.673, "dist": [2, 2, 1, 0, 0, 0, 5]}, {"rep": "Joe Molenaar", "leads": 357, "share": 49.2, "noResp": 3, "avg": 31105.51545480226, "median": 3376.9264999999996, "p90": 71810.764, "dist": [128, 29, 6, 16, 20, 29, 126]}, {"rep": "Mike Wandmaker", "leads": 284, "share": 39.2, "noResp": 0, "avg": 143597.98485211268, "median": 58710.8615, "p90": 441220.317, "dist": [20, 6, 8, 11, 15, 27, 197]}, {"rep": "Unassigned", "leads": 74, "share": 10.2, "noResp": 74, "avg": null, "median": null, "p90": null, "dist": [0, 0, 0, 0, 0, 0, 0]}]}, "repActivity": {"Carson Fossum": {"dials": 11, "answered": 10, "answerRate": 90.9, "over3": 4, "over3Rate": 36.4, "talkSec": 2482, "avgCallSec": 248, "texts": 100, "emails": 2, "totalTouches": 116, "avgTouchesPerLead": 11.6, "touchDist": [0, 0, 3, 7], "leadsOwned": 10, "replied": 7, "replyRate": 70.0, "heatmap": [[0, 0, 0, 0, 0, 0, 0, 0, 0, 0, 0, 0, 0, 0, 0, 0, 0, 3, 0, 4, 0, 0, 0, 0], [0, 0, 0, 0, 0, 0, 0, 0, 0, 0, 2, 0, 0, 3, 0, 0, 0, 0, 0, 1, 2, 13, 0, 0], [0, 0, 0, 0, 0, 0, 0, 0, 0, 0, 0, 0, 0, 0, 3, 0, 6, 0, 1, 3, 7, 5, 0, 0], [0, 0, 0, 0, 0, 0, 2, 1, 0, 0, 0, 0, 0, 0, 0, 0, 1, 0, 0, 2, 3, 2, 0, 0], [0, 0, 0, 0, 0, 0, 0, 1, 2, 0, 0, 0, 0, 0, 0, 1, 0, 0, 2, 0, 0, 0, 0, 0], [0, 0, 0, 0, 0, 0, 0, 0, 0, 0, 0, 0, 0, 1, 0, 0, 3, 0, 0, 1, 0, 0, 4, 3], [0, 0, 0, 0, 0, 0, 0, 0, 0, 0, 0, 1, 0, 0, 0, 1, 8, 3, 18, 0, 0, 0, 0, 0]]}, "Joe Molenaar": {"dials": 458, "answered": 423, "answerRate": 92.4, "over3": 26, "over3Rate": 5.7, "talkSec": 17956, "avgCallSec": 42, "texts": 467, "emails": 29, "totalTouches": 945, "avgTouchesPerLead": 2.6, "touchDist": [80, 89, 144, 41], "leadsOwned": 357, "replied": 105, "replyRate": 29.4, "heatmap": [[0, 0, 0, 0, 0, 0, 0, 5, 1, 2, 19, 17, 2, 4, 1, 4, 1, 3, 3, 0, 0, 0, 4, 2], [0, 0, 0, 0, 0, 0, 0, 1, 14, 54, 41, 7, 15, 34, 28, 31, 12, 6, 0, 4, 2, 0, 0, 0], [0, 0, 0, 0, 0, 0, 0, 2, 3, 32, 48, 13, 10, 19, 17, 16, 11, 6, 1, 5, 4, 6, 7, 0], [0, 0, 0, 0, 0, 1, 2, 0, 7, 16, 18, 4, 23, 14, 9, 19, 11, 23, 4, 2, 3, 0, 0, 0], [0, 0, 0, 0, 0, 0, 1, 1, 8, 12, 11, 7, 24, 24, 2, 11, 20, 0, 4, 5, 2, 0, 0, 5], [0, 0, 0, 0, 0, 0, 0, 3, 3, 4, 19, 2, 1, 5, 8, 3, 10, 4, 15, 18, 2, 1, 0, 0], [3, 0, 0, 0, 0, 0, 4, 3, 0, 1, 4, 2, 6, 5, 8, 4, 2, 0, 0, 0, 0, 4, 0, 0]]}, "Mike Wandmaker": {"dials": 535, "answered": 494, "answerRate": 92.3, "over3": 18, "over3Rate": 3.4, "talkSec": 15007, "avgCallSec": 30, "texts": 251, "emails": 50, "totalTouches": 833, "avgTouchesPerLead": 2.9, "touchDist": [9, 42, 204, 29], "leadsOwned": 284, "replied": 62, "replyRate": 21.8, "heatmap": [[0, 0, 0, 0, 0, 0, 0, 0, 0, 0, 12, 15, 0, 0, 0, 0, 0, 0, 0, 1, 0, 0, 0, 0], [0, 0, 0, 0, 0, 0, 0, 3, 3, 3, 8, 9, 1, 49, 68, 47, 0, 0, 0, 12, 0, 0, 0, 0], [0, 0, 0, 0, 0, 0, 0, 1, 2, 29, 1, 2, 5, 25, 38, 44, 8, 0, 85, 30, 0, 0, 0, 0], [0, 0, 0, 0, 0, 0, 0, 2, 0, 0, 0, 1, 5, 65, 32, 28, 22, 0, 50, 9, 0, 0, 0, 0], [0, 0, 0, 0, 0, 0, 0, 0, 0, 42, 1, 0, 16, 3, 6, 3, 3, 0, 12, 0, 1, 0, 0, 0], [0, 0, 0, 0, 0, 0, 0, 1, 0, 0, 0, 0, 0, 0, 0, 0, 0, 5, 0, 0, 0, 0, 0, 0], [0, 0, 0, 0, 0, 0, 0, 0, 0, 0, 0, 5, 16, 0, 0, 1, 0, 3, 2, 1, 0, 0, 0, 0]]}}}}}